[
  {
    "id": "evt1",
    "facilitatorId": 1,
    "title": "Sacred Sound Ceremony",
    "date": "2026-04-10",
    "time": "19:30–20:30",
    "type": "Sound healing",
    "location": "Ashtari Yoga, Kuta Lombok",
    "summary": "Immersive sound ceremony with singing bowls and sacred instruments.",
    "recurring": false,
    "link": "https://ashtari.yoga/events-in-kuta-lombok/",
    "eventKind": "single"
  },
  {
    "id": "evt2",
    "facilitatorId": 1,
    "title": "Energy Healing Workshop",
    "date": "2026-04-12",
    "time": "11:00–14:00",
    "type": "Energy work",
    "location": "Ashtari Yoga, Kuta Lombok",
    "summary": "A guided workshop focused on restoring vitality and harmony.",
    "recurring": false,
    "link": "https://ashtari.yoga/events-in-kuta-lombok/",
    "eventKind": "single"
  },
  {
    "id": "evt3",
    "facilitatorId": 1,
    "title": "New Moon Sound & Breath Ceremony",
    "date": "2026-04-17",
    "time": "19:30–21:00",
    "type": "Breathwork",
    "location": "Ashtari Yoga, Kuta Lombok",
    "summary": "Breath, ritual and sound healing for intention setting.",
    "recurring": false,
    "link": "https://ashtari.yoga/events-in-kuta-lombok/",
    "eventKind": "single"
  },
  {
    "id": "evt4",
    "facilitatorId": 1,
    "title": "Ecstatic Dance",
    "date": "2026-04-24",
    "time": "19:30–21:00",
    "type": "Dance",
    "location": "Ashtari Yoga, Kuta Lombok",
    "summary": "An uplifting movement evening in the hills above Kuta.",
    "recurring": false,
    "link": "https://ashtari.yoga/events-in-kuta-lombok/",
    "eventKind": "single"
  },
  {
    "id": "evt5",
    "facilitatorId": 2,
    "title": "200H Yoga Teacher Training",
    "date": "2026-04-06",
    "endDate": "2026-04-28",
    "time": "Multi-day program",
    "type": "Training",
    "location": "Mana Yoga Retreat, Kuta Lombok",
    "summary": "Immersive alignment-based vinyasa yoga teacher training.",
    "recurring": false,
    "link": "https://manalombok.com/retreats-training/",
    "eventKind": "multi-day"
  },
  {
    "id": "evt6",
    "facilitatorId": 2,
    "title": "Breathe Space Retreat",
    "date": "2026-03-29",
    "endDate": "2026-04-03",
    "time": "Retreat stay",
    "type": "Retreat",
    "location": "Mana Yoga Retreat, Kuta Lombok",
    "summary": "Breathwork, yin and ceremony on an island retreat.",
    "recurring": false,
    "link": "https://manalombok.com/breathe-space-retreat",
    "eventKind": "multi-day"
  },
  {
    "id": "evt7",
    "facilitatorId": 2,
    "title": "50H Yin Yoga Teacher Training",
    "date": "2026-04-30",
    "endDate": "2026-05-06",
    "time": "Multi-day program",
    "type": "Training",
    "location": "Mana Yoga Retreat, Kuta Lombok",
    "summary": "Yin philosophy, anatomy, meditation and yoga nidra.",
    "recurring": false,
    "link": "https://manalombok.com/2026-50h-yin-yoga-teacher-training/",
    "eventKind": "multi-day"
  },
  {
    "id": "evt8",
    "facilitatorId": 4,
    "title": "New Moon Cacao & Sound Journey",
    "date": "2026-02-16",
    "time": "18:15–20:00",
    "type": "Ceremony",
    "location": "Shanti Yoga Lombok, Kuta Lombok",
    "summary": "Heart-opening cacao and soothing sound journey in collaboration with Dejama Resort.",
    "recurring": false,
    "link": "https://shantiyogalombok.com/event-2/",
    "eventKind": "single"
  },
  {
    "id": "evt9",
    "facilitatorId": 8,
    "title": "Chakra Balancing Meditation",
    "date": "2026-04-07",
    "time": "13:45–14:45",
    "type": "Meditation",
    "location": "Flowers & Fire Seaside Yoga, Gili Air",
    "summary": "Weekly meditation practice focused on balancing the chakras.",
    "recurring": false,
    "link": "https://flowersandfire.yoga/yoga-centre/schedule/",
    "eventKind": "single"
  },
  {
    "id": "evt10",
    "facilitatorId": 8,
    "title": "Shamanic Sound Journey",
    "date": "2026-04-08",
    "time": "18:30–19:30",
    "type": "Sound healing",
    "location": "Flowers & Fire Seaside Yoga, Gili Air",
    "summary": "Evening sound journey by the sea.",
    "recurring": false,
    "link": "https://flowersandfire.yoga/yoga-centre/schedule/",
    "eventKind": "single"
  },
  {
    "id": "evt11",
    "facilitatorId": 8,
    "title": "Kundalini Energy Awakening",
    "date": "2026-04-09",
    "time": "11:00–12:00",
    "type": "Breathwork",
    "location": "Flowers & Fire Yoga Garden, Gili Air",
    "summary": "A weekly awakening practice at the garden studio.",
    "recurring": false,
    "link": "https://flowersandfire.yoga/yoga-centre/schedule/",
    "eventKind": "single"
  },
  {
    "id": "evt12",
    "facilitatorId": 8,
    "title": "Sound Healing",
    "date": "2026-04-10",
    "time": "18:30–19:30",
    "type": "Sound healing",
    "location": "Flowers & Fire Seaside Yoga, Gili Air",
    "summary": "A calming end-of-week sound healing session.",
    "recurring": false,
    "link": "https://flowersandfire.yoga/yoga-centre/schedule/",
    "eventKind": "single"
  },
  {
    "id": "evt13",
    "facilitatorId": 8,
    "title": "Ecstatic Dance",
    "date": "2026-04-11",
    "time": "18:30–20:00",
    "type": "Dance",
    "location": "Flowers & Fire Seaside Yoga, Gili Air",
    "summary": "Free-form movement and community connection.",
    "recurring": false,
    "link": "https://flowersandfire.yoga/yoga-centre/schedule/",
    "eventKind": "single"
  },
  {
    "id": "evt14",
    "facilitatorId": 8,
    "title": "Cacao & Sound Ceremony",
    "date": "2026-04-12",
    "time": "18:45–20:00",
    "type": "Ceremony",
    "location": "Flowers & Fire Seaside Yoga, Gili Air",
    "summary": "Sunday evening cacao and sound ceremony.",
    "recurring": false,
    "link": "https://flowersandfire.yoga/yoga-centre/schedule/",
    "eventKind": "single"
  },
  {
    "id": "evt15",
    "facilitatorId": 9,
    "title": "Aqua Yoga",
    "date": "2026-04-09",
    "time": "11:00",
    "type": "Yoga",
    "location": "H2O Yoga, Gili Air",
    "summary": "A floating yoga experience at H2O.",
    "recurring": false,
    "link": "https://www.h2oyogaandmeditation.com/drop-in-classes/",
    "eventKind": "single"
  },
  {
    "id": "evt16",
    "facilitatorId": 9,
    "title": "Moon Ceremony",
    "date": "2026-04-14",
    "time": "18:30",
    "type": "Ceremony",
    "location": "H2O Yoga, Gili Air",
    "summary": "Lunar ritual evening guided by H2O.",
    "recurring": false,
    "link": "https://www.h2oyogaandmeditation.com/staff/",
    "eventKind": "single"
  },
  {
    "id": "evt17",
    "facilitatorId": 11,
    "title": "Sunrise Flow",
    "date": "2026-04-06",
    "time": "08:30",
    "type": "Yoga",
    "location": "Gili Yoga, Gili Trawangan",
    "summary": "Daily morning flow in the tropical garden studio.",
    "recurring": false,
    "link": "https://www.giliyoga.com/",
    "eventKind": "single"
  },
  {
    "id": "evt18",
    "facilitatorId": 11,
    "title": "Vinyasa",
    "date": "2026-04-06",
    "time": "17:00",
    "type": "Yoga",
    "location": "Gili Yoga, Gili Trawangan",
    "summary": "Evening vinyasa class at the original Gili yoga oasis.",
    "recurring": false,
    "link": "https://www.giliyoga.com/",
    "eventKind": "single"
  },
  {
    "id": "evt19",
    "facilitatorId": 5,
    "title": "Zen Ashtanga Yoga Retreat",
    "date": "2026-04-13",
    "endDate": "2026-04-17",
    "time": "Retreat stay",
    "type": "Retreat",
    "location": "Ikara Yoga, Lombok",
    "summary": "Week-long Ashtanga retreat open to practitioners of all levels.",
    "recurring": false,
    "link": "https://www.ikarayoga.com/retreat/",
    "eventKind": "multi-day"
  },
  {
    "id": "evt20",
    "facilitatorId": 2,
    "title": "Balance & Restore Retreat",
    "date": "2026-07-08",
    "endDate": "2026-07-11",
    "time": "Retreat stay",
    "type": "Retreat",
    "location": "Mana Yoga Retreat, Kuta Lombok",
    "summary": "Grounding vinyasa, yin, sound, breathwork meditation and cacao celebration.",
    "recurring": false,
    "link": "https://manalombok.com/",
    "eventKind": "multi-day"
  },
  {
    "id": "evt21",
    "facilitatorId": 2,
    "title": "The Renewal Retreat",
    "date": "2026-06-22",
    "endDate": "2026-06-27",
    "time": "Retreat stay",
    "type": "Retreat",
    "location": "Mana Yoga Retreat, Kuta Lombok",
    "summary": "A six-day journey of movement, self-discovery and clarity.",
    "recurring": false,
    "link": "https://manalombok.com/",
    "eventKind": "multi-day"
  },
  {
    "id": "evt22",
    "facilitatorId": 8,
    "title": "Women’s Circle – Reclaiming the Cycle",
    "date": "2026-04-06",
    "time": "18:45–20:00",
    "type": "Circle",
    "location": "Flowers & Fire Seaside Yoga, Gili Air",
    "summary": "Weekly women’s circle at the seaside studio.",
    "recurring": false,
    "link": "https://flowersandfire.yoga/yoga-centre/schedule/",
    "eventKind": "single"
  }
]